s6r_bitwarden_cli/__init__.py
s6r_bitwarden_cli/__main__.py
s6r_bitwarden_cli/bitwarden.py
s6r_bitwarden_cli-1.0.7.dist-info/LICENSE
s6r_bitwarden_cli-1.0.7.dist-info/METADATA
s6r_bitwarden_cli-1.0.7.dist-info/WHEEL
s6r_bitwarden_cli-1.0.7.dist-info/entry_points.txt
s6r_bitwarden_cli-1.0.7.dist-info/top_level.txt
s6r_bitwarden_cli-1.0.7.dist-info/RECORD
