Metadata-Version: 2.1
Name: s6r-bitwarden-cli
Version: 1.0.7
Summary: Interact easily with Bitwarden client
Author-email: Michel Perrocheau <michel@scalizer.fr>
License: GNU LESSER GENERAL PUBLIC LICENSE
Project-URL: Homepage, https://github.com/ScalizerOrg/s6r-bitwarden-cli
Keywords: bitwarden,vault,python,cli,bw
Classifier: License :: OSI Approved :: GNU Lesser General Public License v3 (LGPLv3)
Classifier: Programming Language :: Python
Classifier: Programming Language :: Python :: 3
Requires-Python: >=3.9
License-File: LICENSE
Requires-Dist: pexpect
Provides-Extra: dev
Requires-Dist: twine ; extra == 'dev'
Requires-Dist: bumpver ; extra == 'dev'
Requires-Dist: pip-tools ; extra == 'dev'
Requires-Dist: pytest ; extra == 'dev'
Requires-Dist: check-manifest ; extra == 'dev'
